complexnet/__init__.py
complexnet/util.py
complexnet/layers/__init__.py
complexnet/layers/complex_core.py
complexnet/layers/complex_recurrent.py
complexnet-0.1.6.dist-info/METADATA
complexnet-0.1.6.dist-info/RECORD
complexnet-0.1.6.dist-info/WHEEL
complexnet-0.1.6.dist-info/top_level.txt
